{
  "testStartTime" : 1755618977.398025000,
  "testEndTime" : 1755619042.552260000,
  "totalDuration" : 65.154235000,
  "terminationReason" : "DURATION_COMPLETED",
  "finalPhase" : "COMPLETED",
  "totalRequests" : 1200,
  "successfulRequests" : 1200,
  "failedRequests" : 0,
  "errorRate" : 0.0,
  "averageResponseTime" : 108.75083333333333,
  "p50ResponseTime" : 94,
  "p95ResponseTime" : 171,
  "p99ResponseTime" : 182,
  "minResponseTime" : 87,
  "maxResponseTime" : 326,
  "averageThroughput" : 18.46153846153846,
  "peakThroughput" : 20.4,
  "statusCodeDistribution" : {
    "201" : 1200
  },
  "backPressureEvents" : 0,
  "scheduledRequests" : 1200,
  "errorSummary" : {
    "totalErrors" : 0,
    "errorsByType" : { },
    "errorsByMessage" : { },
    "errorsByPhase" : { }
  },
  "topErrors" : [ ],
  "slaViolationSummary" : {
    "totalViolations" : 0,
    "violationsByType" : { },
    "firstViolation" : null,
    "lastViolation" : null
  },
  "allSlaViolations" : [ ],
  "userMetricsSummary" : null,
  "windowSummaries" : [ {
    "windowNumber" : 1,
    "startTime" : 1755618977.398025000,
    "endTime" : 1755618982.403048000,
    "windowSizeSeconds" : 5,
    "requestCount" : 0,
    "successfulRequests" : 0,
    "failedRequests" : 0,
    "errorRate" : 0.0,
    "averageResponseTime" : 0.0,
    "p50ResponseTime" : 0,
    "p95ResponseTime" : 0,
    "p99ResponseTime" : 0,
    "minResponseTime" : 0,
    "maxResponseTime" : 0,
    "throughput" : 0.0,
    "usersStarted" : [ ],
    "usersCompleted" : [ ],
    "backPressureEvents" : 0,
    "slaViolationCount" : 0,
    "errorCount" : 0
  }, {
    "windowNumber" : 2,
    "startTime" : 1755618982.403048000,
    "endTime" : 1755618987.399596000,
    "windowSizeSeconds" : 5,
    "requestCount" : 98,
    "successfulRequests" : 98,
    "failedRequests" : 0,
    "errorRate" : 0.0,
    "averageResponseTime" : 109.53061224489795,
    "p50ResponseTime" : 95,
    "p95ResponseTime" : 169,
    "p99ResponseTime" : 212,
    "minResponseTime" : 89,
    "maxResponseTime" : 212,
    "throughput" : 19.6,
    "usersStarted" : [ ],
    "usersCompleted" : [ ],
    "backPressureEvents" : 0,
    "slaViolationCount" : 0,
    "errorCount" : 0
  }, {
    "windowNumber" : 3,
    "startTime" : 1755618987.399596000,
    "endTime" : 1755618992.401216000,
    "windowSizeSeconds" : 5,
    "requestCount" : 100,
    "successfulRequests" : 100,
    "failedRequests" : 0,
    "errorRate" : 0.0,
    "averageResponseTime" : 112.09,
    "p50ResponseTime" : 95,
    "p95ResponseTime" : 176,
    "p99ResponseTime" : 183,
    "minResponseTime" : 89,
    "maxResponseTime" : 326,
    "throughput" : 20.0,
    "usersStarted" : [ ],
    "usersCompleted" : [ ],
    "backPressureEvents" : 0,
    "slaViolationCount" : 0,
    "errorCount" : 0
  }, {
    "windowNumber" : 4,
    "startTime" : 1755618992.401216000,
    "endTime" : 1755618997.400702000,
    "windowSizeSeconds" : 5,
    "requestCount" : 100,
    "successfulRequests" : 100,
    "failedRequests" : 0,
    "errorRate" : 0.0,
    "averageResponseTime" : 108.37,
    "p50ResponseTime" : 94,
    "p95ResponseTime" : 174,
    "p99ResponseTime" : 182,
    "minResponseTime" : 89,
    "maxResponseTime" : 183,
    "throughput" : 20.0,
    "usersStarted" : [ ],
    "usersCompleted" : [ ],
    "backPressureEvents" : 0,
    "slaViolationCount" : 0,
    "errorCount" : 0
  }, {
    "windowNumber" : 5,
    "startTime" : 1755618997.400702000,
    "endTime" : 1755619002.401474000,
    "windowSizeSeconds" : 5,
    "requestCount" : 100,
    "successfulRequests" : 100,
    "failedRequests" : 0,
    "errorRate" : 0.0,
    "averageResponseTime" : 108.97,
    "p50ResponseTime" : 93,
    "p95ResponseTime" : 170,
    "p99ResponseTime" : 177,
    "minResponseTime" : 88,
    "maxResponseTime" : 180,
    "throughput" : 20.0,
    "usersStarted" : [ ],
    "usersCompleted" : [ ],
    "backPressureEvents" : 0,
    "slaViolationCount" : 0,
    "errorCount" : 0
  }, {
    "windowNumber" : 6,
    "startTime" : 1755619002.401474000,
    "endTime" : 1755619007.399244000,
    "windowSizeSeconds" : 5,
    "requestCount" : 100,
    "successfulRequests" : 100,
    "failedRequests" : 0,
    "errorRate" : 0.0,
    "averageResponseTime" : 106.83,
    "p50ResponseTime" : 93,
    "p95ResponseTime" : 165,
    "p99ResponseTime" : 182,
    "minResponseTime" : 88,
    "maxResponseTime" : 183,
    "throughput" : 20.0,
    "usersStarted" : [ ],
    "usersCompleted" : [ ],
    "backPressureEvents" : 0,
    "slaViolationCount" : 0,
    "errorCount" : 0
  }, {
    "windowNumber" : 7,
    "startTime" : 1755619007.399244000,
    "endTime" : 1755619012.401296000,
    "windowSizeSeconds" : 5,
    "requestCount" : 100,
    "successfulRequests" : 100,
    "failedRequests" : 0,
    "errorRate" : 0.0,
    "averageResponseTime" : 109.38,
    "p50ResponseTime" : 94,
    "p95ResponseTime" : 175,
    "p99ResponseTime" : 181,
    "minResponseTime" : 87,
    "maxResponseTime" : 182,
    "throughput" : 20.0,
    "usersStarted" : [ ],
    "usersCompleted" : [ ],
    "backPressureEvents" : 0,
    "slaViolationCount" : 0,
    "errorCount" : 0
  }, {
    "windowNumber" : 8,
    "startTime" : 1755619012.401296000,
    "endTime" : 1755619017.397946000,
    "windowSizeSeconds" : 5,
    "requestCount" : 100,
    "successfulRequests" : 100,
    "failedRequests" : 0,
    "errorRate" : 0.0,
    "averageResponseTime" : 107.95,
    "p50ResponseTime" : 94,
    "p95ResponseTime" : 171,
    "p99ResponseTime" : 178,
    "minResponseTime" : 90,
    "maxResponseTime" : 180,
    "throughput" : 20.0,
    "usersStarted" : [ ],
    "usersCompleted" : [ ],
    "backPressureEvents" : 0,
    "slaViolationCount" : 0,
    "errorCount" : 0
  }, {
    "windowNumber" : 9,
    "startTime" : 1755619017.397946000,
    "endTime" : 1755619022.402265000,
    "windowSizeSeconds" : 5,
    "requestCount" : 100,
    "successfulRequests" : 100,
    "failedRequests" : 0,
    "errorRate" : 0.0,
    "averageResponseTime" : 108.22,
    "p50ResponseTime" : 94,
    "p95ResponseTime" : 168,
    "p99ResponseTime" : 173,
    "minResponseTime" : 89,
    "maxResponseTime" : 184,
    "throughput" : 20.0,
    "usersStarted" : [ ],
    "usersCompleted" : [ ],
    "backPressureEvents" : 0,
    "slaViolationCount" : 0,
    "errorCount" : 0
  }, {
    "windowNumber" : 10,
    "startTime" : 1755619022.402265000,
    "endTime" : 1755619027.399978000,
    "windowSizeSeconds" : 5,
    "requestCount" : 99,
    "successfulRequests" : 99,
    "failedRequests" : 0,
    "errorRate" : 0.0,
    "averageResponseTime" : 108.88888888888889,
    "p50ResponseTime" : 94,
    "p95ResponseTime" : 178,
    "p99ResponseTime" : 184,
    "minResponseTime" : 88,
    "maxResponseTime" : 184,
    "throughput" : 19.8,
    "usersStarted" : [ ],
    "usersCompleted" : [ ],
    "backPressureEvents" : 0,
    "slaViolationCount" : 0,
    "errorCount" : 0
  }, {
    "windowNumber" : 11,
    "startTime" : 1755619027.399978000,
    "endTime" : 1755619032.401774000,
    "windowSizeSeconds" : 5,
    "requestCount" : 102,
    "successfulRequests" : 102,
    "failedRequests" : 0,
    "errorRate" : 0.0,
    "averageResponseTime" : 108.38235294117646,
    "p50ResponseTime" : 94,
    "p95ResponseTime" : 172,
    "p99ResponseTime" : 179,
    "minResponseTime" : 88,
    "maxResponseTime" : 181,
    "throughput" : 20.4,
    "usersStarted" : [ ],
    "usersCompleted" : [ ],
    "backPressureEvents" : 0,
    "slaViolationCount" : 0,
    "errorCount" : 0
  }, {
    "windowNumber" : 12,
    "startTime" : 1755619032.401774000,
    "endTime" : 1755619037.397896000,
    "windowSizeSeconds" : 5,
    "requestCount" : 99,
    "successfulRequests" : 99,
    "failedRequests" : 0,
    "errorRate" : 0.0,
    "averageResponseTime" : 108.08080808080808,
    "p50ResponseTime" : 94,
    "p95ResponseTime" : 173,
    "p99ResponseTime" : 178,
    "minResponseTime" : 88,
    "maxResponseTime" : 178,
    "throughput" : 19.8,
    "usersStarted" : [ ],
    "usersCompleted" : [ ],
    "backPressureEvents" : 0,
    "slaViolationCount" : 0,
    "errorCount" : 0
  }, {
    "windowNumber" : 13,
    "startTime" : 1755619037.397896000,
    "endTime" : 1755619042.401155000,
    "windowSizeSeconds" : 5,
    "requestCount" : 101,
    "successfulRequests" : 101,
    "failedRequests" : 0,
    "errorRate" : 0.0,
    "averageResponseTime" : 108.46534653465346,
    "p50ResponseTime" : 94,
    "p95ResponseTime" : 171,
    "p99ResponseTime" : 182,
    "minResponseTime" : 89,
    "maxResponseTime" : 182,
    "throughput" : 20.2,
    "usersStarted" : [ ],
    "usersCompleted" : [ ],
    "backPressureEvents" : 0,
    "slaViolationCount" : 0,
    "errorCount" : 0
  } ],
  "windowAnalysis" : {
    "totalWindows" : 12,
    "windowSize" : 5,
    "throughputStats" : {
      "count" : 12,
      "sum" : 239.8,
      "min" : 19.6,
      "max" : 20.4,
      "average" : 19.983333333333334
    },
    "responseTimeStats" : {
      "count" : 12,
      "sum" : 1305.1580086904248,
      "min" : 106.83,
      "max" : 112.09,
      "average" : 108.76316739086873
    },
    "peakWindow" : {
      "windowNumber" : 11,
      "startTime" : 1755619027.399978000,
      "windowSizeSeconds" : 5,
      "endTime" : 1755619032.401774000,
      "requestCount" : 102,
      "successfulRequests" : 102,
      "failedRequests" : 0,
      "totalResponseTime" : 11055,
      "minResponseTime" : 88,
      "maxResponseTime" : 181,
      "responseTimes" : [ 154, 99, 133, 90, 91, 95, 91, 99, 91, 95, 107, 174, 163, 113, 92, 91, 92, 94, 91, 95, 91, 100, 151, 137, 94, 95, 98, 94, 93, 93, 89, 173, 124, 157, 108, 93, 94, 92, 94, 92, 90, 90, 149, 179, 130, 90, 90, 92, 94, 88, 91, 89, 172, 122, 102, 156, 92, 94, 92, 94, 95, 91, 88, 99, 149, 128, 96, 93, 92, 98, 92, 92, 93, 172, 122, 152, 104, 93, 93, 99, 93, 91, 95, 100, 149, 181, 129, 93, 90, 92, 96, 92, 92, 94, 169, 124, 152, 103, 95, 92, 94, 90 ],
      "errorCount" : 0,
      "slaViolationCount" : 0,
      "usersStarted" : [ ],
      "usersCompleted" : [ ],
      "backPressureEvents" : 0,
      "errorRate" : 0.0,
      "throughput" : 20.4,
      "averageResponseTime" : 108.38235294117646,
      "p50ResponseTime" : 94,
      "p95ResponseTime" : 172,
      "p99ResponseTime" : 179
    }
  }
}